napari_serverkit/__init__.py
napari_serverkit/__main__.py
napari_serverkit/_version.py
napari_serverkit/napari.yaml
napari_serverkit/widgets/__init__.py
napari_serverkit/widgets/algorithm_widget.py
napari_serverkit/widgets/http_runner_widget.py
napari_serverkit/widgets/napari_results.py
napari_serverkit/widgets/parameter_panel.py
napari_serverkit/widgets/runner_widget.py
napari_serverkit/widgets/serverkit_http_widget.py
napari_serverkit/widgets/serverkit_widget.py
napari_serverkit/widgets/task_manager.py
napari_serverkit-0.1.2.dist-info/licenses/LICENSE
napari_serverkit-0.1.2.dist-info/METADATA
napari_serverkit-0.1.2.dist-info/WHEEL
napari_serverkit-0.1.2.dist-info/entry_points.txt
napari_serverkit-0.1.2.dist-info/top_level.txt
napari_serverkit-0.1.2.dist-info/RECORD
