Metadata-Version: 2.4
Name: napari-serverkit
Version: 0.1.2
Summary: Napari client for the imaging-server-kit project.
Author-email: Mallory Wittwer <mallory.wittwer@epfl.ch>
License: Copyright (c) 2024, EPFL
Project-URL: homepage, https://github.com/EPFL-Center-for-Imaging/napari-serverkit
Project-URL: repository, https://github.com/EPFL-Center-for-Imaging/napari-serverkit
Classifier: Development Status :: 2 - Pre-Alpha
Classifier: License :: OSI Approved :: BSD License
Classifier: Programming Language :: Python :: 3
Classifier: Programming Language :: Python :: 3.9
Classifier: Programming Language :: Python :: 3.10
Classifier: Programming Language :: Python :: 3.11
Classifier: Programming Language :: Python :: 3.12
Classifier: Topic :: Scientific/Engineering :: Image Processing
Classifier: Framework :: napari
Requires-Python: >=3.9
License-File: LICENSE
Requires-Dist: napari[all]>=0.4.16
Requires-Dist: qtpy
Requires-Dist: imaging-server-kit>=0.1
Requires-Dist: napari-toolkit
Dynamic: license-file
